wslink/__init__.py
wslink/launcher.py
wslink/publish.py
wslink/server.py
wslink/uri.py
wslink/websocket.py
wslink/wslinktypes.py
wslink/backends/__init__.py
wslink/backends/aiohttp/__init__.py
wslink/backends/aiohttp/launcher.py
wslink/backends/aiohttp/progress_frame.py
wslinklc-0.0.1.dist-info/METADATA
wslinklc-0.0.1.dist-info/WHEEL
wslinklc-0.0.1.dist-info/top_level.txt
wslinklc-0.0.1.dist-info/RECORD
