Metadata-Version: 2.1
Name: wslinklc
Version: 0.0.1
Summary: Python/JavaScript library for communicating over WebSocket, with workarounds to publish messages synchronously, by Luminary. A fork of https://github.com/kitware/wslink
Home-page: https://github.com/yasushi-saito/wslink
Author: Kitware, Inc.
Author-email: yasushi.saito@gmail.com
License: BSD-3-Clause
Keywords: websocket javascript rpc pubsub
Platform: UNKNOWN
Classifier: Development Status :: 5 - Production/Stable
Classifier: Environment :: Web Environment
Classifier: License :: OSI Approved :: BSD License
Classifier: Operating System :: OS Independent
Classifier: Programming Language :: Python
Classifier: Programming Language :: Python :: 3
Classifier: Programming Language :: Python :: 3.5
Classifier: Programming Language :: Python :: 3.6
Classifier: Programming Language :: Python :: 3.7
Classifier: Programming Language :: Python :: 3.8
Classifier: Programming Language :: Python :: 3.9
Classifier: Topic :: Software Development :: Libraries :: Python Modules
Requires-Dist: aiohttp
